{"cameraMode":{"drawMode":0,"name":"Shaded","section":"Shading Mode"},"sceneLighting":false,"audioPlay":false,"sceneViewState":{"m_AlwaysRefresh":false,"showFog":true,"showSkybox":false,"showFlares":true,"showImageEffects":true,"showParticleSystems":true,"showVisualEffectGraphs":true,"m_FxEnabled":true},"in2DMode":false,"pivot":{"x":0.2515716552734375,"y":7.34260368347168,"z":0.22410202026367188},"rotation":{"x":0.279930979013443,"y":-0.6687083840370178,"z":0.3024841547012329,"w":0.6188524961471558},"size":11.24559497833252,"orthographic":false}